garoupa/__init__.py
garoupa/algebra/__init__.py
garoupa/algebra/abs/__init__.py
garoupa/algebra/abs/element.py
garoupa/algebra/cyclic/__init__.py
garoupa/algebra/cyclic/nat.py
garoupa/algebra/cyclic/natm.py
garoupa/algebra/cyclic/z.py
garoupa/algebra/cyclic/zm.py
garoupa/algebra/dihedral/__init__.py
garoupa/algebra/dihedral/d.py
garoupa/algebra/dihedral/dr.py
garoupa/algebra/dihedral/ds.py
garoupa/algebra/math.py
garoupa/algebra/matrix/__init__.py
garoupa/algebra/matrix/aux.py
garoupa/algebra/matrix/fullm.py
garoupa/algebra/matrix/fullmat.py
garoupa/algebra/matrix/group.py
garoupa/algebra/matrix/m.py
garoupa/algebra/matrix/m128bit.py
garoupa/algebra/matrix/m8bit.py
garoupa/algebra/matrix/mat.py
garoupa/algebra/matrix/mat128bit.py
garoupa/algebra/matrix/mat8bit.py
garoupa/algebra/npmath.py
garoupa/algebra/product/__init__.py
garoupa/algebra/product/product.py
garoupa/algebra/product/tuple.py
garoupa/algebra/symmetric/__init__.py
garoupa/algebra/symmetric/perm.py
garoupa/algebra/symmetric/s.py
garoupa/config.py
garoupa/groups.py
garoupa/hosh.py
garoupa/misc/__init__.py
garoupa/misc/colors.py
garoupa/misc/core.py
garoupa/misc/encoding/__init__.py
garoupa/misc/encoding/base.py
garoupa/misc/encoding/base777.py
garoupa/misc/exception.py
garoupa/misc/helper.py
garoupa/misc/identity.py
garoupa/misc/math.py
garoupa-3.250405.1.dist-info/LICENSE
garoupa-3.250405.1.dist-info/METADATA
garoupa-3.250405.1.dist-info/WHEEL
garoupa-3.250405.1.dist-info/RECORD
