Metadata-Version: 2.3
Name: garoupa
Version: 3.250405.1
Summary: Predictable operable hash-based identifiers and abstract algebra groups
License: GPL
Author: davips
Author-email: dpsabc@gmail.com
Requires-Python: >=3.9
Classifier: License :: Other/Proprietary License
Classifier: Programming Language :: Python :: 3
Classifier: Programming Language :: Python :: 3.9
Classifier: Programming Language :: Python :: 3.10
Classifier: Programming Language :: Python :: 3.11
Classifier: Programming Language :: Python :: 3.12
Classifier: Programming Language :: Python :: 3.13
Provides-Extra: algebra
Provides-Extra: experiments
Provides-Extra: native
Requires-Dist: ansi2html (==1.6.0)
Requires-Dist: bigfloat (>=0.4.0,<0.5.0) ; extra == "experiments"
Requires-Dist: blake3 (>=1.0.4,<2.0.0)
Requires-Dist: colored (==1.4.2)
Requires-Dist: pathos (>=0.2.8,<0.3.0) ; extra == "algebra"
Requires-Dist: progress (>=1.6,<2.0) ; extra == "algebra"
Requires-Dist: setuptools (>=78.1.0,<79.0.0)
Requires-Dist: wheel (>=0.37.0,<0.38.0)
